ex2/优先编码器/encode42.v
module encode42(x,en,y);
  input  [3:0] x;
  input  en;
  output reg [1:0]y;
  integer i;
  always @(x or en) begin
    if (en) begin
      y = 0;
      for( i = 0; i <= 3; i = i+1)
          if(x[i] == 1)  y = i[1:0];
    end
    else  y = 0;
  end
endmodule

ex2/优先编码器/dump.vcd
$version Generated by VerilatedVcd $end
$timescale 1s $end

 $scope module TOP $end
  $var wire  1 $ en $end
  $var wire  4 # x [3:0] $end
  $var wire  2 % y [1:0] $end
  $scope module encode42 $end
   $var wire  1 $ en $end
   $var wire 32 & i [31:0] $end
   $var wire  4 # x [3:0] $end
   $var wire  2 % y [1:0] $end
  $upscope $end
 $upscope $end
$enddefinitions $end


#1
b0000 #
0$
b00 %
b00000000000000000000000000000000 &
#2
b0001 #
#3
b0010 #
#4
b0011 #
#5
b0100 #
#6
b0101 #
#7
b0110 #
#8
b0111 #
#9
b1000 #
#10
b1001 #
#11
b1010 #
#12
b1011 #
#13
b1100 #
#14
b1101 #
#15
b1110 #
#16
b1111 #
#17
b0000 #
#18
b0000 #
1$
b00000000000000000000000000000100 &
#19
b0001 #
#20
b0010 #
b01 %
#21
b0011 #
#22
b0100 #
b10 %
#23
b0101 #
#24
b0110 #
#25
b0111 #
#26
b1000 #
b11 %
#27
b1001 #
#28
b1010 #
#29
b1011 #
#30
b1100 #
#31
b1101 #
#32
b1110 #
#33
b1111 #
#34
b0000 #
b00 %
b00000011000000010000001100000001 &
