双控开关/top.v
module top(
	input a,
	input b,
	output f
);

	assign f = a ^ b;
endmodule

双控开关/wave.vcd
$version Generated by VerilatedVcd $end
$timescale 1ps $end

 $scope module TOP $end
  $var wire  1 # a $end
  $var wire  1 $ b $end
  $var wire  1 % f $end
  $scope module top $end
   $var wire  1 # a $end
   $var wire  1 $ b $end
   $var wire  1 % f $end
  $upscope $end
 $upscope $end
$enddefinitions $end


#0
1#
0$
1%
#1
1$
0%
#2
#3
0#
0$
#4
1#
1$
#5
0#
1%
#6
#7
1#
0$
#8
0#
0%
#9
#10
1#
1%
#11
1$
0%
#12
0#
0$
#13
1$
1%
#14
1#
0%
#15
0$
1%
#16
0#
0%
#17
1#
1$
#18
0$
1%
