ex1/vmux42/mux41.v
module mux41(a,s,y);
  input  [3:0] a;  // 声明一个wire型输入变量a，其变量宽度是4位的。
  input  [1:0] s;  // 声明一个wire型输入变量s，其变量宽度是2位的。
  output reg y;   // 声明一个1位reg型的输出变量y。

  always @ (s or a)
    case (s)
      0: y = a[0];
      1: y = a[1];
      2: y = a[2];
      3: y = a[3];
      default: y = 1'b0;
    endcase

endmodule

ex1/vmux42/dump.vcd
$version Generated by VerilatedVcd $end
$timescale 1s $end

 $scope module TOP $end
  $var wire  4 # a [3:0] $end
  $var wire  2 $ s [1:0] $end
  $var wire  1 % y $end
  $scope module mux41 $end
   $var wire  4 # a [3:0] $end
   $var wire  2 $ s [1:0] $end
   $var wire  1 % y $end
  $upscope $end
 $upscope $end
$enddefinitions $end


#1
b1110 #
b00 $
0%
#2
b0001 #
1%
#3
b1110 #
b01 $
#4
b0010 #
#5
b1010 #
b10 $
0%
#6
b0100 #
1%
#7
b0111 #
b11 $
0%
#8
b1001 #
1%
